numbox/__init__.py
numbox/core/__init__.py
numbox/core/configurations.py
numbox/core/any/__init__.py
numbox/core/any/any_type.py
numbox/core/any/content_wrap.py
numbox/core/any/erased_type.py
numbox/core/bindings/__init__.py
numbox/core/bindings/_c.py
numbox/core/bindings/_math.py
numbox/core/bindings/_sqlite.py
numbox/core/bindings/call.py
numbox/core/bindings/signatures.py
numbox/core/bindings/utils.py
numbox/core/proxy/__init__.py
numbox/core/proxy/proxy.py
numbox/core/variable/__init__.py
numbox/core/variable/variable.py
numbox/core/work/__init__.py
numbox/core/work/builder.py
numbox/core/work/builder_utils.py
numbox/core/work/combine_utils.py
numbox/core/work/explain.py
numbox/core/work/loader_utils.py
numbox/core/work/lowlevel_work_utils.py
numbox/core/work/node.py
numbox/core/work/node_base.py
numbox/core/work/print_tree.py
numbox/core/work/work.py
numbox/core/work/work_utils.py
numbox/utils/__init__.py
numbox/utils/highlevel.py
numbox/utils/lowlevel.py
numbox/utils/meminfo.py
numbox/utils/standard.py
numbox/utils/timer.py
numbox/utils/void_type.py
numbox-0.3.4.dist-info/LICENSE
numbox-0.3.4.dist-info/METADATA
numbox-0.3.4.dist-info/WHEEL
numbox-0.3.4.dist-info/top_level.txt
numbox-0.3.4.dist-info/RECORD
