Metadata-Version: 2.1
Name: numbox
Version: 0.3.4
Author: Mikhail Goykhman
License: MIT License (with Citation Clause)
Keywords: llvmlite,numba,numpy
Requires-Python: >=3.10
License-File: LICENSE
Requires-Dist: numba<0.64.0,>=0.60.0
Provides-Extra: docs
Requires-Dist: sphinx==8.1.3; extra == "docs"
Requires-Dist: sphinx-sitemap==2.7.2; extra == "docs"
Requires-Dist: sphinx-rtd-theme; extra == "docs"
